{
  "collectionName": "components_talent_builds_talent_builds",
  "info": {
    "displayName": "Talent Builds",
    "icon": "code",
    "description": ""
  },
  "options": {},
  "attributes": {
    "wowImportString": {
      "type": "string"
    },
    "talentBuildPic": {
      "type": "media",
      "multiple": false,
      "required": false,
      "allowedTypes": [
        "images",
        "files",
        "videos",
        "audios"
      ]
    },
    "buildName": {
      "type": "string"
    },
    "keyTalentIcons": {
      "type": "media",
      "multiple": true,
      "required": false,
      "allowedTypes": [
        "images",
        "files",
        "videos",
        "audios"
      ]
    },
    "quickSummary": {
      "type": "string"
    },
    "heroSpec": {
      "type": "enumeration",
      "enum": [
        "mountain_thane",
        "slayer",
        "colossus"
      ]
    }
  }
}
